pyrokid_cxr_clientm/__init__.py
pyrokid_cxr_clientm/_version.py
pyrokid_cxr_clientm/cxr_socket_protocol.py
pyrokid_cxr_clientm/libcaps.py
pyrokid_cxr_clientm/controllers/__init__.py
pyrokid_cxr_clientm/controllers/audio_controller.py
pyrokid_cxr_clientm/customview/__init__.py
pyrokid_cxr_clientm/customview/image_view_props.py
pyrokid_cxr_clientm/customview/linear_layout_props.py
pyrokid_cxr_clientm/customview/props.py
pyrokid_cxr_clientm/customview/relative_layout_props.py
pyrokid_cxr_clientm/customview/self_view.py
pyrokid_cxr_clientm/customview/text_view_props.py
pyrokid_cxr_clientm/customview/update_view.py
pyrokid_cxr_clientm/customview/utils.py
pyrokid_cxr_clientm/extend/__init__.py
pyrokid_cxr_clientm/extend/constants.py
pyrokid_cxr_clientm/extend/callbacks/__init__.py
pyrokid_cxr_clientm/extend/callbacks/apk_status_callback.py
pyrokid_cxr_clientm/extend/callbacks/audio_scene_id_callback.py
pyrokid_cxr_clientm/extend/callbacks/bluetooth_status_callback.py
pyrokid_cxr_clientm/extend/callbacks/glass_info_result_callback.py
pyrokid_cxr_clientm/extend/callbacks/glass_version_callback.py
pyrokid_cxr_clientm/extend/callbacks/photo_path_callback.py
pyrokid_cxr_clientm/extend/callbacks/photo_result_callback.py
pyrokid_cxr_clientm/extend/callbacks/send_status_callback.py
pyrokid_cxr_clientm/extend/callbacks/sync_status_callback.py
pyrokid_cxr_clientm/extend/callbacks/unsync_num_result_callback.py
pyrokid_cxr_clientm/extend/callbacks/wifi_list_callback.py
pyrokid_cxr_clientm/extend/callbacks/wifi_p2p_status_callback.py
pyrokid_cxr_clientm/extend/controllers/__init__.py
pyrokid_cxr_clientm/extend/controllers/file_controller.py
pyrokid_cxr_clientm/extend/controllers/wifi_controller.py
pyrokid_cxr_clientm/extend/infos/__init__.py
pyrokid_cxr_clientm/extend/infos/glass_info.py
pyrokid_cxr_clientm/extend/infos/glass_setting_item.py
pyrokid_cxr_clientm/extend/infos/icon_info.py
pyrokid_cxr_clientm/extend/infos/rk_app_info.py
pyrokid_cxr_clientm/extend/infos/rk_wifi_info.py
pyrokid_cxr_clientm-0.0.4a4.dist-info/licenses/LICENSE
pyrokid_cxr_clientm-0.0.4a4.dist-info/METADATA
pyrokid_cxr_clientm-0.0.4a4.dist-info/WHEEL
pyrokid_cxr_clientm-0.0.4a4.dist-info/top_level.txt
pyrokid_cxr_clientm-0.0.4a4.dist-info/RECORD
