Metadata-Version: 2.4
Name: pyrokid_cxr_clientm
Version: 0.0.4a4
Summary: A python port of the com.rokid.cxr.client-m Java library.
Author-email: Miniontoby <author@example.com>
Project-URL: Homepage, https://github.com/Miniontoby/pyrokid_cxr_clientm
Project-URL: Documentation, https://pyrokid-cxr-clientm.readthedocs.io/en/latest/
Project-URL: Repository, https://github.com/Miniontoby/pyrokid_cxr_clientm.git
Project-URL: Bug Tracker, https://github.com/Miniontoby/pyrokid_cxr_clientm/issues
Keywords: rokid,cxr,client-m,glasses,rokid glasses,com.rokid.cxr.client-m
Classifier: Development Status :: 3 - Alpha
Classifier: Intended Audience :: Developers
Classifier: Operating System :: OS Independent
Classifier: Programming Language :: Python :: 3
Classifier: Programming Language :: Python :: 3.7
Classifier: Programming Language :: Python :: 3.8
Classifier: Programming Language :: Python :: 3.9
Classifier: Programming Language :: Python :: 3.10
Classifier: Programming Language :: Python :: 3.11
Requires-Python: >=3.7
License-File: LICENSE
Requires-Dist: bleak
Requires-Dist: pybluez; python_version < "3.9"
Requires-Dist: tzlocal
Requires-Dist: pycryptodome
Requires-Dist: requests
Requires-Dist: dataclasses_json
Requires-Dist: faster-whisper
Requires-Dist: numpy
Requires-Dist: soundfile
Requires-Dist: scipy
Dynamic: license-file
